gelf_formatter-1.0.0.dist-info/licenses/LICENSE
gelfformatter/__init__.py
gelfformatter/formatter.py
gelfformatter/py.typed
gelfformatter/version.py
gelf_formatter-1.0.0.dist-info/METADATA
gelf_formatter-1.0.0.dist-info/WHEEL
gelf_formatter-1.0.0.dist-info/top_level.txt
gelf_formatter-1.0.0.dist-info/RECORD
