Metadata-Version: 2.4
Name: gelf-formatter
Version: 1.0.0
Summary: GELF formatter for the Python standard library logging module.
Author: Joao Pereira
License-Expression: MIT
Project-URL: Homepage, https://github.com/joaodrp/gelf-formatter
Project-URL: Repository, https://github.com/joaodrp/gelf-formatter
Project-URL: Issues, https://github.com/joaodrp/gelf-formatter/issues
Keywords: gelf,graylog,logger,logging,log,json
Classifier: Development Status :: 5 - Production/Stable
Classifier: Intended Audience :: Developers
Classifier: Operating System :: OS Independent
Classifier: Programming Language :: Python :: 3
Classifier: Programming Language :: Python :: 3.10
Classifier: Programming Language :: Python :: 3.11
Classifier: Programming Language :: Python :: 3.12
Classifier: Programming Language :: Python :: 3.13
Classifier: Programming Language :: Python :: 3.14
Classifier: Topic :: Software Development :: Libraries :: Python Modules
Classifier: Topic :: System :: Logging
Requires-Python: >=3.10
License-File: LICENSE
Dynamic: license-file
